{
  "parent": "CCitadel_Item",
  "metadata": [],
  "fields": [
    {
      "name": "m_bFlying",
      "type": {
        "name": "bool",
        "category": 0
      },
      "metadata": [
        {
          "name": "MNetworkUserGroup",
          "value": "LocalPlayerOwnerAndObserversExclusive"
        }
      ]
    },
    {
      "name": "m_bSummoning",
      "type": {
        "name": "bool",
        "category": 0
      },
      "metadata": [
        {
          "name": "MNetworkUserGroup",
          "value": "LocalPlayerOwnerAndObserversExclusive"
        }
      ]
    }
  ]
}